qiskit_qulacs/__init__.py
qiskit_qulacs/adapter.py
qiskit_qulacs/backend_utils.py
qiskit_qulacs/qulacs_backend.py
qiskit_qulacs/qulacs_estimator.py
qiskit_qulacs/qulacs_estimator_gradient.py
qiskit_qulacs/qulacs_job.py
qiskit_qulacs/qulacs_provider.py
qiskit_qulacs/qulacs_sampler.py
qiskit_qulacs/version.py
qiskit_qulacs-0.1.0.dist-info/LICENSE.txt
qiskit_qulacs-0.1.0.dist-info/METADATA
qiskit_qulacs-0.1.0.dist-info/WHEEL
qiskit_qulacs-0.1.0.dist-info/top_level.txt
qiskit_qulacs-0.1.0.dist-info/RECORD
