Metadata-Version: 2.1
Name: qiskit_qulacs
Version: 0.1.0
Summary: Qiskit Qulacs to execute Qiskit programs using Qulacs as backend.
Author-email: Gopal Ramesh Dahale <dahalegopal27@gmail.com>
License: Copyright 2021 IBM and its contributors
Project-URL: Homepage, https://github.com/Gopal-Dahale/qiskit-qulacs
Project-URL: Bug Tracker, https://github.com/Gopal-Dahale/qiskit-qulacs/issues
Project-URL: Documentation, https://qiskit-qulacs.netlify.app/
Project-URL: Repository, https://github.com/Gopal-Dahale/qiskit-qulacs
Classifier: Intended Audience :: Developers
Classifier: Intended Audience :: Science/Research
Classifier: License :: OSI Approved :: Apache Software License
Classifier: Natural Language :: English
Classifier: Operating System :: MacOS
Classifier: Operating System :: POSIX :: Linux
Classifier: Operating System :: Microsoft :: Windows
Classifier: Programming Language :: Python :: 3 :: Only
Classifier: Programming Language :: Python :: 3.8
Classifier: Programming Language :: Python :: 3.9
Classifier: Programming Language :: Python :: 3.10
Classifier: Programming Language :: Python :: 3.11
Classifier: Programming Language :: Python :: 3.12
Classifier: Topic :: Scientific/Engineering :: Physics
Requires-Python: >=3.8
License-File: LICENSE.txt
Requires-Dist: certifi >=2021.5.30
Requires-Dist: importlib-metadata >=4.8.1
Requires-Dist: qiskit-aer >=0.12.2
Requires-Dist: qiskit >=1.0.0
Requires-Dist: qiskit-algorithms >=0.3.0
Requires-Dist: qulacs >=0.5.0
Provides-Extra: dev
Requires-Dist: coverage >=5.5 ; extra == 'dev'
Requires-Dist: matplotlib >=3.3 ; extra == 'dev'
Requires-Dist: qiskit-nature >=0.7.2 ; extra == 'dev'
Requires-Dist: pyscf >=2.5.0 ; extra == 'dev'
Requires-Dist: pylatexenc >=1.4 ; extra == 'dev'
Requires-Dist: pylint >=2.9.5 ; extra == 'dev'
Requires-Dist: nbqa >=1.1.1 ; extra == 'dev'
Requires-Dist: treon >=0.1.3 ; extra == 'dev'
Requires-Dist: pytest >=6.2.5 ; extra == 'dev'
Requires-Dist: pytest-randomly >=1.2.0 ; extra == 'dev'
Requires-Dist: mypy >=0.780 ; extra == 'dev'
Requires-Dist: mypy-extensions >=0.4.3 ; extra == 'dev'
Requires-Dist: jupyter-sphinx >=0.3.2 ; extra == 'dev'
Requires-Dist: nbsphinx >=0.8.8 ; extra == 'dev'
Requires-Dist: sphinx-autodoc-typehints >=1.17.0 ; extra == 'dev'
Requires-Dist: reno >=3.5.0 ; extra == 'dev'
Requires-Dist: black[jupyter] ~=22.1 ; extra == 'dev'
Requires-Dist: tox ==3.24.5 ; extra == 'dev'
Requires-Dist: ddt !=1.4.0,!=1.4.3,>=1.2.0 ; extra == 'dev'
Requires-Dist: myst-parser >=1.0.0 ; extra == 'dev'
Requires-Dist: qiskit-sphinx-theme >=1.14.0 ; extra == 'dev'
